simplemapreduce/__about__.py
simplemapreduce/__init__.py
simplemapreduce/executors.py
simplemapreduce/types.py
simplemapreduce-0.0.2.dist-info/METADATA
simplemapreduce-0.0.2.dist-info/WHEEL
simplemapreduce-0.0.2.dist-info/licenses/LICENSE.txt
simplemapreduce-0.0.2.dist-info/RECORD
