Metadata-Version: 2.4
Name: simplemapreduce
Version: 0.0.2
Summary: A simple map reduce multithreaded library
Author-email: Yiannis Giannelos <johngiannelos@gmail.com>
License-Expression: MIT
License-File: LICENSE.txt
Requires-Python: >=3.8
